powerblog_toolkit/__init__.py
powerblog_toolkit/analysis.py
powerblog_toolkit/serper_fetcher.py
powerblog_toolkit/sheets.py
powerblog_toolkit-0.3.1.dist-info/licenses/LICENSE
powerblog_toolkit-0.3.1.dist-info/METADATA
powerblog_toolkit-0.3.1.dist-info/WHEEL
powerblog_toolkit-0.3.1.dist-info/top_level.txt
powerblog_toolkit-0.3.1.dist-info/RECORD
