Metadata-Version: 2.4
Name: powerblog-toolkit
Version: 0.3.1
Summary: Fetch and analyze search data from Serper.dev and manage results in Google Sheets.
Home-page: https://github.com/samarth-agrawal-86/powerblog_toolkit
Author: Samarth Agrawal
Author-email: Samarth <samarth.agrawal.86@gmail.com>
License: MIT
Requires-Python: >=3.6
License-File: LICENSE
Requires-Dist: pandas
Requires-Dist: requests
Requires-Dist: numpy
Requires-Dist: gspread
Requires-Dist: gspread-dataframe
Requires-Dist: google-auth
Dynamic: author
Dynamic: home-page
Dynamic: license-file
Dynamic: requires-python
